src/__init__.py
src/aimhardest.py
src/exceptions.py
aimhardest-0.0.1.dist-info/LICENSE
aimhardest-0.0.1.dist-info/WHEEL
aimhardest-0.0.1.dist-info/METADATA
aimhardest-0.0.1.dist-info/RECORD
