Metadata-Version: 2.1
Name: aimhardest
Version: 0.0.1
Summary: 
Author: blazaid
Author-email: alberto.da@gmail.com
Requires-Python: >=3.10,<4.0
Classifier: Programming Language :: Python :: 3
Classifier: Programming Language :: Python :: 3.10
Classifier: Programming Language :: Python :: 3.11
Requires-Dist: requests (>=2.28.1,<3.0.0)
